Metadata-Version: 2.1
Name: wellcome
Version: 0.1
Summary: Wellcome card generator
Home-page: https://github.com/krypton-byte/wellcome
Author: Krypton Byte
Author-email: galaxyvplus6434@gmail.com
License: MIT
Keywords: Wellcome,Card
Platform: UNKNOWN
Classifier: Development Status :: 3 - Alpha
Classifier: Intended Audience :: Developers
Classifier: Topic :: Software Development :: Build Tools
Classifier: License :: OSI Approved :: MIT License
Classifier: Programming Language :: Python :: 3.8
Classifier: Programming Language :: Python :: 3.9
